{
  "version": "1.0",
  "name": "Yole App Navigation Test Bank",
  "description": "Navigation flow tests for all screens, tabs, drawer, deep links, rotation, and theme switching",
  "metadata": {
    "author": "vasic-digital",
    "app": "Yole",
    "version": "1.0.0",
    "bluff_audit_status": "converted-by-bank-prose-to-http.py",
    "bluff_audit_date": "2026-04-29"
  },
  "test_cases": [
    {
      "id": "NAV-MAIN-001",
      "name": "Navigate to Files screen",
      "category": "functional",
      "priority": "critical",
      "platforms": [
        "android",
        "web",
        "desktop"
      ],
      "steps": [
        {
          "name": "Launch app",
          "action": "Open Yole application",
          "expected": "App launches to default screen",
          "_conversion_note": "manual-review-required"
        },
        {
          "name": "Tap Files tab",
          "action": "Tap/click 'Files' in bottom navigation bar or sidebar",
          "expected": "Files screen displayed with file browser or recent files",
          "_conversion_note": "manual-review-required"
        }
      ],
      "tags": [
        "navigation",
        "main-screen",
        "files"
      ],
      "documentation_refs": [
        {
          "type": "user_guide",
          "section": "1.1",
          "path": "docs/USER_MANUAL_ANDROID.md"
        }
      ],
      "estimated_duration": "10s",
      "expected_result": "Files screen accessible from main navigation"
    },
    {
      "id": "NAV-MAIN-002",
      "name": "Navigate to Todo screen",
      "category": "functional",
      "priority": "critical",
      "platforms": [
        "android",
        "web",
        "desktop"
      ],
      "steps": [
        {
          "name": "Tap Todo tab",
          "action": "Tap/click 'Todo' in navigation bar",
          "expected": "Todo screen shown with todo.txt task list or empty state",
          "_conversion_note": "manual-review-required"
        }
      ],
      "tags": [
        "navigation",
        "main-screen",
        "todo"
      ],
      "estimated_duration": "10s",
      "expected_result": "Todo screen accessible from main navigation"
    },
    {
      "id": "NAV-MAIN-003",
      "name": "Navigate to QuickNote screen",
      "category": "functional",
      "priority": "critical",
      "platforms": [
        "android",
        "web",
        "desktop"
      ],
      "steps": [
        {
          "name": "Tap QuickNote tab",
          "action": "Tap/click 'QuickNote' in navigation bar",
          "expected": "QuickNote editor screen displayed",
          "_conversion_note": "manual-review-required"
        },
        {
          "name": "Verify quick note editor",
          "action": "Check that text input is immediately available",
          "expected": "Editor ready for input without extra taps",
          "_conversion_note": "manual-review-required"
        }
      ],
      "tags": [
        "navigation",
        "main-screen",
        "quicknote"
      ],
      "estimated_duration": "10s",
      "expected_result": "QuickNote screen accessible and editor ready"
    },
    {
      "id": "NAV-MAIN-004",
      "name": "Navigate to More/Settings screen",
      "category": "functional",
      "priority": "high",
      "platforms": [
        "android",
        "web",
        "desktop"
      ],
      "steps": [
        {
          "name": "Tap More tab",
          "action": "Tap/click 'More' or overflow menu in navigation bar",
          "expected": "More screen or settings menu opens",
          "_conversion_note": "manual-review-required"
        },
        {
          "name": "Verify menu items",
          "action": "Check visible menu options",
          "expected": "Settings, About, Storage, Theme options visible",
          "_conversion_note": "manual-review-required"
        }
      ],
      "tags": [
        "navigation",
        "main-screen",
        "more",
        "settings"
      ],
      "estimated_duration": "10s",
      "expected_result": "More screen shows all top-level settings options"
    },
    {
      "id": "NAV-SUB-001",
      "name": "Open Editor from file browser",
      "category": "functional",
      "priority": "critical",
      "platforms": [
        "android",
        "web",
        "desktop"
      ],
      "steps": [
        {
          "name": "Browse to a text file",
          "action": "Navigate file browser to a .md file",
          "expected": "File listing visible",
          "_conversion_note": "manual-review-required"
        },
        {
          "name": "Open file",
          "action": "Tap/click the file",
          "expected": "Editor screen opens with file content",
          "_conversion_note": "manual-review-required"
        },
        {
          "name": "Verify back navigation",
          "action": "Press Back or close editor",
          "expected": "Returns to file browser at same location",
          "_conversion_note": "manual-review-required"
        }
      ],
      "tags": [
        "navigation",
        "sub-screen",
        "editor",
        "file-browser"
      ],
      "estimated_duration": "20s",
      "expected_result": "Editor opens from browser and back navigation works"
    },
    {
      "id": "NAV-SUB-002",
      "name": "Switch between Editor and Preview",
      "category": "functional",
      "priority": "critical",
      "platforms": [
        "android",
        "web",
        "desktop"
      ],
      "steps": [
        {
          "name": "Open a markdown file in editor",
          "action": "Open any .md file",
          "expected": "Editor showing markdown source",
          "_conversion_note": "manual-review-required"
        },
        {
          "name": "Switch to Preview tab",
          "action": "Tap/click 'Preview' tab",
          "expected": "HTML preview rendered",
          "_conversion_note": "manual-review-required"
        },
        {
          "name": "Switch back to Edit tab",
          "action": "Tap/click 'Edit' tab",
          "expected": "Source editor restored, cursor position preserved",
          "_conversion_note": "manual-review-required"
        }
      ],
      "tags": [
        "navigation",
        "sub-screen",
        "editor",
        "preview"
      ],
      "estimated_duration": "20s",
      "expected_result": "Edit/Preview tab switching works without losing cursor position"
    },
    {
      "id": "NAV-SUB-003",
      "name": "Open Settings screen",
      "category": "functional",
      "priority": "high",
      "platforms": [
        "android",
        "web",
        "desktop"
      ],
      "steps": [
        {
          "name": "Navigate to Settings",
          "action": "Go to More > Settings",
          "expected": "Settings screen opens",
          "_conversion_note": "manual-review-required"
        },
        {
          "name": "Check settings categories",
          "action": "Scroll through settings list",
          "expected": "Categories: Editor, Appearance, Storage, About visible",
          "_conversion_note": "manual-review-required"
        },
        {
          "name": "Return to previous screen",
          "action": "keypress: KEYCODE_BACK",
          "expected": "Returns to More screen",
          "_original_action": "Press Back"
        }
      ],
      "tags": [
        "navigation",
        "sub-screen",
        "settings"
      ],
      "estimated_duration": "20s",
      "expected_result": "Settings screen navigable with back return"
    },
    {
      "id": "NAV-CTRL-001",
      "name": "Bottom navigation bar switches screens",
      "category": "functional",
      "priority": "critical",
      "platforms": [
        "android",
        "web"
      ],
      "steps": [
        {
          "name": "Tap each tab in order",
          "action": "Tap Files, Todo, QuickNote, More in sequence",
          "expected": "Each screen displays correctly on each tap",
          "_conversion_note": "manual-review-required"
        },
        {
          "name": "Re-tap current tab",
          "action": "While on Files screen, tap Files again",
          "expected": "Scrolls to top or refreshes list (no double-navigation)",
          "_conversion_note": "manual-review-required"
        }
      ],
      "tags": [
        "navigation",
        "bottom-bar",
        "tabs"
      ],
      "estimated_duration": "25s",
      "expected_result": "Bottom navigation bar works correctly for all tabs"
    },
    {
      "id": "NAV-CTRL-002",
      "name": "Drawer menu navigation (Android)",
      "category": "functional",
      "priority": "high",
      "platforms": [
        "android"
      ],
      "steps": [
        {
          "name": "Open drawer",
          "action": "Swipe right from left edge or tap hamburger menu",
          "expected": "Navigation drawer slides open",
          "_conversion_note": "manual-review-required"
        },
        {
          "name": "Select item from drawer",
          "action": "Tap a navigation destination in the drawer",
          "expected": "Correct screen opens, drawer closes",
          "_conversion_note": "manual-review-required"
        },
        {
          "name": "Close drawer without navigating",
          "action": "Tap outside drawer or swipe left",
          "expected": "Drawer closes, current screen unchanged",
          "_conversion_note": "manual-review-required"
        }
      ],
      "tags": [
        "navigation",
        "drawer",
        "android"
      ],
      "estimated_duration": "25s",
      "expected_result": "Navigation drawer opens, navigates, and closes correctly"
    },
    {
      "id": "NAV-CTRL-003",
      "name": "System back button navigation (Android)",
      "category": "functional",
      "priority": "critical",
      "platforms": [
        "android"
      ],
      "steps": [
        {
          "name": "Navigate into sub-screen",
          "action": "Open a file in the editor",
          "expected": "Editor screen visible",
          "_conversion_note": "manual-review-required"
        },
        {
          "name": "Press system back",
          "action": "Press Android system back button",
          "expected": "Returns to file browser",
          "_conversion_note": "manual-review-required"
        },
        {
          "name": "Press system back again",
          "action": "Press back from file browser",
          "expected": "Returns to main Files tab or minimizes app",
          "_conversion_note": "manual-review-required"
        }
      ],
      "tags": [
        "navigation",
        "back-button",
        "android",
        "system"
      ],
      "estimated_duration": "20s",
      "expected_result": "System back navigates the back stack correctly"
    },
    {
      "id": "NAV-CTRL-004",
      "name": "Sidebar navigation (Desktop)",
      "category": "functional",
      "priority": "critical",
      "platforms": [
        "desktop"
      ],
      "steps": [
        {
          "name": "Verify sidebar visible",
          "action": "adb_shell: monkey -p desktop -c android.intent.category.LAUNCHER 1",
          "expected": "Left sidebar with navigation items visible",
          "_original_action": "Launch desktop app"
        },
        {
          "name": "Click sidebar items",
          "action": "playwright: click text=Files, Todo, QuickNote in sidebar",
          "expected": "Each screen loads in main content area",
          "_original_action": "Click Files, Todo, QuickNote in sidebar"
        },
        {
          "name": "Collapse sidebar",
          "action": "playwright: click text=sidebar toggle",
          "expected": "Sidebar collapses to icon-only mode",
          "_original_action": "Click sidebar toggle button"
        },
        {
          "name": "Expand sidebar",
          "action": "playwright: click text=toggle again",
          "expected": "Sidebar expands with labels",
          "_original_action": "Click toggle again"
        }
      ],
      "tags": [
        "navigation",
        "sidebar",
        "desktop"
      ],
      "estimated_duration": "25s",
      "expected_result": "Desktop sidebar navigation works and collapses"
    },
    {
      "id": "NAV-TAB-001",
      "name": "Open multiple files in tabs",
      "category": "functional",
      "priority": "high",
      "platforms": [
        "android",
        "web",
        "desktop"
      ],
      "steps": [
        {
          "name": "Open first file",
          "action": "Open file1.md in editor",
          "expected": "Tab 1 shows file1.md",
          "_conversion_note": "manual-review-required"
        },
        {
          "name": "Open second file",
          "action": "Open file2.txt from file browser",
          "expected": "Tab 2 created, switches to file2.txt",
          "_conversion_note": "manual-review-required"
        },
        {
          "name": "Open third file",
          "action": "Open file3.org",
          "expected": "Tab 3 created for file3.org",
          "_conversion_note": "manual-review-required"
        },
        {
          "name": "Verify tab bar",
          "action": "Check tab bar has 3 tabs",
          "expected": "3 tabs visible with correct filenames",
          "_conversion_note": "manual-review-required"
        }
      ],
      "tags": [
        "navigation",
        "tabs",
        "multi-file"
      ],
      "estimated_duration": "35s",
      "expected_result": "Multiple files open in separate tabs"
    },
    {
      "id": "NAV-TAB-002",
      "name": "Switch between open tabs",
      "category": "functional",
      "priority": "high",
      "platforms": [
        "android",
        "web",
        "desktop"
      ],
      "steps": [
        {
          "name": "Open two files in tabs",
          "action": "Open file1.md and file2.txt",
          "expected": "Both tabs present",
          "_conversion_note": "manual-review-required"
        },
        {
          "name": "Switch to tab 1",
          "action": "Tap/click tab 1 (file1.md)",
          "expected": "file1.md content displayed",
          "_conversion_note": "manual-review-required"
        },
        {
          "name": "Switch to tab 2",
          "action": "Tap/click tab 2 (file2.txt)",
          "expected": "file2.txt content displayed",
          "_conversion_note": "manual-review-required"
        }
      ],
      "tags": [
        "navigation",
        "tabs",
        "switching"
      ],
      "estimated_duration": "20s",
      "expected_result": "Tab switching preserves content of each open file"
    },
    {
      "id": "NAV-TAB-003",
      "name": "Close a tab",
      "category": "functional",
      "priority": "high",
      "platforms": [
        "android",
        "web",
        "desktop"
      ],
      "steps": [
        {
          "name": "Open two files in tabs",
          "action": "Open file1.md and file2.txt",
          "expected": "2 tabs visible",
          "_conversion_note": "manual-review-required"
        },
        {
          "name": "Close tab 1",
          "action": "Tap 'X' on tab 1 or swipe tab away",
          "expected": "Tab 1 closed, tab 2 becomes active",
          "_conversion_note": "manual-review-required"
        },
        {
          "name": "Verify single tab remains",
          "action": "Check tab bar",
          "expected": "Only file2.txt tab remains",
          "_conversion_note": "manual-review-required"
        }
      ],
      "tags": [
        "navigation",
        "tabs",
        "close-tab"
      ],
      "estimated_duration": "20s",
      "expected_result": "Tab close works, remaining tabs unaffected"
    },
    {
      "id": "NAV-TAB-004",
      "name": "Close unsaved tab prompts confirmation",
      "category": "functional",
      "priority": "high",
      "platforms": [
        "android",
        "web",
        "desktop"
      ],
      "steps": [
        {
          "name": "Open file and make unsaved changes",
          "action": "Open file.md and type new content without saving",
          "expected": "Unsaved indicator visible (dot or asterisk on tab)",
          "_conversion_note": "manual-review-required"
        },
        {
          "name": "Close the unsaved tab",
          "action": "Attempt to close the tab",
          "expected": "Dialog: 'Unsaved changes — Save, Discard, Cancel?'",
          "_conversion_note": "manual-review-required"
        },
        {
          "name": "Choose Discard",
          "action": "Tap 'Discard'",
          "expected": "Tab closed, changes lost",
          "_conversion_note": "manual-review-required"
        }
      ],
      "tags": [
        "navigation",
        "tabs",
        "unsaved",
        "confirmation"
      ],
      "estimated_duration": "25s",
      "expected_result": "Unsaved changes prompt shown before closing tab"
    },
    {
      "id": "NAV-ROT-001",
      "name": "Screen rotation preserves editor state (Android)",
      "category": "functional",
      "priority": "high",
      "platforms": [
        "android"
      ],
      "steps": [
        {
          "name": "Open file in editor",
          "action": "Open a markdown file, type some text",
          "expected": "Editor in portrait mode with content",
          "_conversion_note": "manual-review-required"
        },
        {
          "name": "Rotate to landscape",
          "action": "Rotate device 90 degrees",
          "expected": "Editor redraws in landscape, content and cursor preserved",
          "_conversion_note": "manual-review-required"
        },
        {
          "name": "Rotate back to portrait",
          "action": "Rotate device back",
          "expected": "Editor in portrait, scroll position preserved",
          "_conversion_note": "manual-review-required"
        }
      ],
      "tags": [
        "navigation",
        "rotation",
        "android",
        "state-preservation"
      ],
      "estimated_duration": "25s",
      "expected_result": "Rotation preserves editor content and cursor position"
    },
    {
      "id": "NAV-ROT-002",
      "name": "Screen rotation preserves file browser position (Android)",
      "category": "functional",
      "priority": "medium",
      "platforms": [
        "android"
      ],
      "steps": [
        {
          "name": "Browse to nested directory",
          "action": "Navigate 3 levels deep in file browser",
          "expected": "Nested directory shown",
          "_conversion_note": "manual-review-required"
        },
        {
          "name": "Rotate device",
          "action": "Rotate to landscape",
          "expected": "Same directory shown in landscape layout",
          "_conversion_note": "manual-review-required"
        },
        {
          "name": "Verify path preserved",
          "action": "Check breadcrumb",
          "expected": "Breadcrumb shows same path as before rotation",
          "_conversion_note": "manual-review-required"
        }
      ],
      "tags": [
        "navigation",
        "rotation",
        "android",
        "file-browser"
      ],
      "estimated_duration": "20s",
      "expected_result": "File browser path preserved across rotation"
    },
    {
      "id": "NAV-DEEP-001",
      "name": "Open text file via system file manager (Android)",
      "category": "functional",
      "priority": "high",
      "platforms": [
        "android"
      ],
      "steps": [
        {
          "name": "Open a .md file from Files app",
          "action": "In Android Files app, tap a .md file and choose Yole",
          "expected": "Yole opens with the selected file in editor",
          "_conversion_note": "manual-review-required"
        },
        {
          "name": "Verify file content",
          "action": "Check editor shows correct content",
          "expected": "File loaded correctly via intent",
          "_conversion_note": "manual-review-required"
        }
      ],
      "tags": [
        "navigation",
        "deep-link",
        "intent",
        "android"
      ],
      "estimated_duration": "20s",
      "expected_result": "Yole handles file open intents from other apps"
    },
    {
      "id": "NAV-DEEP-002",
      "name": "Share text to Yole creates new note (Android)",
      "category": "functional",
      "priority": "medium",
      "platforms": [
        "android"
      ],
      "steps": [
        {
          "name": "Share text from another app",
          "action": "In browser, select text and share to Yole",
          "expected": "Yole opens with shared text pre-filled in QuickNote or new file",
          "_conversion_note": "manual-review-required"
        },
        {
          "name": "Verify content",
          "action": "Check editor content",
          "expected": "Shared text visible in editor",
          "_conversion_note": "manual-review-required"
        }
      ],
      "tags": [
        "navigation",
        "share-intent",
        "android",
        "quicknote"
      ],
      "estimated_duration": "25s",
      "expected_result": "Share intent populates new note with shared text"
    },
    {
      "id": "NAV-SETT-001",
      "name": "Settings persist across app restart",
      "category": "functional",
      "priority": "critical",
      "platforms": [
        "android",
        "web",
        "desktop"
      ],
      "steps": [
        {
          "name": "Change a setting",
          "action": "Enable line numbers in Settings > Editor",
          "expected": "Line numbers appear in editor",
          "_conversion_note": "manual-review-required"
        },
        {
          "name": "Restart app",
          "action": "Force-close and relaunch Yole",
          "expected": "App launches",
          "_conversion_note": "manual-review-required"
        },
        {
          "name": "Verify setting persisted",
          "action": "Open any file in editor",
          "expected": "Line numbers still enabled",
          "_conversion_note": "manual-review-required"
        }
      ],
      "tags": [
        "navigation",
        "settings",
        "persistence",
        "restart"
      ],
      "estimated_duration": "35s",
      "expected_result": "Settings changes survive app restart"
    },
    {
      "id": "NAV-THEME-001",
      "name": "Switch to dark theme",
      "category": "functional",
      "priority": "high",
      "platforms": [
        "android",
        "web",
        "desktop"
      ],
      "steps": [
        {
          "name": "Open theme settings",
          "action": "Go to Settings > Appearance > Theme",
          "expected": "Theme picker visible: Light, Dark, System",
          "_conversion_note": "manual-review-required"
        },
        {
          "name": "Select Dark",
          "action": "Tap/click 'Dark'",
          "expected": "App switches to dark theme immediately",
          "_conversion_note": "manual-review-required"
        },
        {
          "name": "Verify dark theme",
          "action": "Check backgrounds and text colors",
          "expected": "Dark backgrounds, light text throughout the app",
          "_conversion_note": "manual-review-required"
        }
      ],
      "tags": [
        "navigation",
        "theme",
        "dark-mode",
        "appearance"
      ],
      "estimated_duration": "20s",
      "expected_result": "Dark theme applied immediately to all screens"
    },
    {
      "id": "NAV-THEME-002",
      "name": "System theme follows OS setting",
      "category": "functional",
      "priority": "medium",
      "platforms": [
        "android",
        "desktop"
      ],
      "steps": [
        {
          "name": "Set theme to System",
          "action": "Select 'System' in theme settings",
          "expected": "Theme matches current OS dark/light mode",
          "_conversion_note": "manual-review-required"
        },
        {
          "name": "Toggle OS dark mode",
          "action": "Switch OS to dark mode (or back to light)",
          "expected": "Yole switches theme to match OS setting",
          "_conversion_note": "manual-review-required"
        }
      ],
      "tags": [
        "navigation",
        "theme",
        "system-theme",
        "os-integration"
      ],
      "estimated_duration": "25s",
      "expected_result": "System theme follows OS dark/light mode changes"
    }
  ]
}
